my_library/__init__.py
my_library/my_module.py
my_library_template-0.1.0.dist-info/licenses/LICENSE
my_library_template-0.1.0.dist-info/METADATA
my_library_template-0.1.0.dist-info/WHEEL
my_library_template-0.1.0.dist-info/top_level.txt
my_library_template-0.1.0.dist-info/RECORD
