Metadata-Version: 2.4
Name: my-library-template
Version: 0.1.0
Summary: A minimal template for Python packaging
Author-email: my name <me@gmail.com>
Keywords: example,template,library
Classifier: Programming Language :: Python :: 3
Classifier: License :: OSI Approved :: MIT License
Classifier: Operating System :: OS Independent
Requires-Python: >=3.7
License-File: LICENSE
Dynamic: license-file
